{
  "code": "shire-shovel",
  "class": "ItemTool",
  "durability": 120,
  "tool": "shovel",
  "miningspeed": {
    "soil": 4.725,
    "gravel": 3.78,
    "sand": 3.78
  },
  "attributes": {
    "attackpower": 1.2,
    "attackrange": 2.0,
    "tooltier": 1,
    "miningspeed": {
      "stone": 1.0,
      "wood": 1.0,
      "soil": 1.5
    }
  },
  "textures": {
    "texture": {
      "base": "lotr:item/shire-shovel"
    }
  },
  "creativeInventory": {
    "lotr": [
      "*"
    ]
  },
  "shape": {
    "base": "lotr:item/shire-shovel"
  }
}